odoo/addons/stock_release_channel_shipment_advice/README.rst
odoo/addons/stock_release_channel_shipment_advice/__init__.py
odoo/addons/stock_release_channel_shipment_advice/__manifest__.py
odoo/addons/stock_release_channel_shipment_advice/i18n/es.po
odoo/addons/stock_release_channel_shipment_advice/i18n/fr.po
odoo/addons/stock_release_channel_shipment_advice/i18n/it.po
odoo/addons/stock_release_channel_shipment_advice/i18n/stock_release_channel_shipment_advice.pot
odoo/addons/stock_release_channel_shipment_advice/models/__init__.py
odoo/addons/stock_release_channel_shipment_advice/models/shipment_advice.py
odoo/addons/stock_release_channel_shipment_advice/models/stock_release_channel.py
odoo/addons/stock_release_channel_shipment_advice/readme/CONTRIBUTORS.md
odoo/addons/stock_release_channel_shipment_advice/readme/DESCRIPTION.md
odoo/addons/stock_release_channel_shipment_advice/readme/USAGE.md
odoo/addons/stock_release_channel_shipment_advice/static/description/icon.png
odoo/addons/stock_release_channel_shipment_advice/static/description/index.html
odoo/addons/stock_release_channel_shipment_advice/tests/__init__.py
odoo/addons/stock_release_channel_shipment_advice/tests/test_stock_release_channel_shipment_advice.py
odoo/addons/stock_release_channel_shipment_advice/views/shipment_advice.xml
odoo/addons/stock_release_channel_shipment_advice/views/stock_release_channel.xml
odoo/addons/stock_release_channel_shipment_advice/wizards/__init__.py
odoo/addons/stock_release_channel_shipment_advice/wizards/shipment_advice_planner.py
odoo/addons/stock_release_channel_shipment_advice/wizards/shipment_advice_planner.xml
odoo_addon_stock_release_channel_shipment_advice-18.0.1.0.0.2.dist-info/METADATA
odoo_addon_stock_release_channel_shipment_advice-18.0.1.0.0.2.dist-info/WHEEL
odoo_addon_stock_release_channel_shipment_advice-18.0.1.0.0.2.dist-info/top_level.txt
odoo_addon_stock_release_channel_shipment_advice-18.0.1.0.0.2.dist-info/RECORD
